modelica_builder/__init__.py
modelica_builder/builder.py
modelica_builder/config.py
modelica_builder/edit.py
modelica_builder/measures/measure_base.py
modelica_builder/model.py
modelica_builder/modelica_mos_file.py
modelica_builder/modelica_parser/README.rst
modelica_builder/modelica_parser/__init__.py
modelica_builder/modelica_parser/modelica.g4
modelica_builder/modelica_parser/modelica.interp
modelica_builder/modelica_parser/modelica.tokens
modelica_builder/modelica_parser/modelicaLexer.interp
modelica_builder/modelica_parser/modelicaLexer.py
modelica_builder/modelica_parser/modelicaLexer.tokens
modelica_builder/modelica_parser/modelicaListener.py
modelica_builder/modelica_parser/modelicaParser.py
modelica_builder/modelica_parser/utils.py
modelica_builder/modelica_project.py
modelica_builder/package_parser.py
modelica_builder/selector.py
modelica_builder/templates/package.mot
modelica_builder/templates/package_base.mot
modelica_builder/transformation.py
modelica_builder/transformer.py
modelica_builder-0.6.0.dist-info/AUTHORS.rst
modelica_builder-0.6.0.dist-info/LICENSE.md
modelica_builder-0.6.0.dist-info/METADATA
modelica_builder-0.6.0.dist-info/WHEEL
modelica_builder-0.6.0.dist-info/RECORD
