Metadata-Version: 2.1
Name: modelica-builder
Version: 0.6.0
Summary: Modelica builder enables programmatic parsing and modification of Modelica files.
Home-page: https://github.com/urbanopt/modelica-builder/releases
License: BSD-3-Clause
Keywords: Modelica,Physics-based Modeling,Abstract Syntax Tree,AST
Author: Nicholas Long
Author-email: nicholas.long@nrel.gov
Requires-Python: >=3.9,<3.14
Classifier: Development Status :: 4 - Beta
Classifier: Environment :: Console
Classifier: Intended Audience :: Developers
Classifier: Intended Audience :: Science/Research
Classifier: License :: OSI Approved :: BSD License
Classifier: Programming Language :: Python :: 3
Classifier: Programming Language :: Python :: 3.9
Classifier: Programming Language :: Python :: 3.10
Classifier: Programming Language :: Python :: 3.11
Classifier: Programming Language :: Python :: 3.12
Classifier: Programming Language :: Python :: 3.13
Classifier: Topic :: Scientific/Engineering
Requires-Dist: antlr4-python3-runtime (==4.13.2)
Requires-Dist: certifi (>=2024.8.30,<2025.0.0)
Requires-Dist: jinja2 (>=3.1.4,<3.2.0)
Requires-Dist: pathspec (>=0.11.2,<0.12.0)
Project-URL: Documentation, https://github.com/urbanopt/modelica-builder
Project-URL: Repository, https://github.com/urbanopt/modelica-builder
